celx/__about__.py
celx/__init__.py
celx/__main__.py
celx/application.py
celx/callbacks.py
celx/lua.py
celx/parsing.py
tests/__init__.py
sh40_celx-0.8.1.dist-info/METADATA
sh40_celx-0.8.1.dist-info/WHEEL
sh40_celx-0.8.1.dist-info/entry_points.txt
sh40_celx-0.8.1.dist-info/licenses/LICENSE
sh40_celx-0.8.1.dist-info/RECORD
